{
    "/js/app.js": "/js/app.js",
    "/js/suggestions.js": "/js/suggestions.js",
    "/css/app.css": "/css/app.css",
    "/css/app-mobile.css": "/css/app-mobile.css",
    "/img/big_request.png": "/img/big_request.png",
    "/img/description.png": "/img/description.png",
    "/img/go.svg": "/img/go.svg",
    "/img/head1.png": "/img/head1.png",
    "/img/head_bg.jpg": "/img/head_bg.jpg",
    "/img/icon-1.png": "/img/icon-1.png",
    "/img/icon-2.png": "/img/icon-2.png",
    "/img/icon-3.png": "/img/icon-3.png",
    "/img/icon1-near.png": "/img/icon1-near.png",
    "/img/icon1a.svg": "/img/icon1a.svg",
    "/img/icon2-tools.png": "/img/icon2-tools.png",
    "/img/icon3-rouble.png": "/img/icon3-rouble.png",
    "/img/icon4-mp.png": "/img/icon4-mp.png",
    "/img/logo-big-v.svg": "/img/logo-big-v.svg",
    "/img/logo-simple.svg": "/img/logo-simple.svg",
    "/img/logo.png": "/img/logo.png",
    "/img/logo.svg": "/img/logo.svg",
    "/img/logo1.png": "/img/logo1.png",
    "/img/logo1a-horiz.svg": "/img/logo1a-horiz.svg",
    "/img/logo1a.svg": "/img/logo1a.svg",
    "/img/logo2.png": "/img/logo2.png",
    "/img/logo3.png": "/img/logo3.png",
    "/img/robot2.png": "/img/robot2.png",
    "/img/splash-bg.jpg": "/img/splash-bg.jpg",
    "/img/star.svg": "/img/star.svg",
    "/img/suggest.png": "/img/suggest.png",
    "/img/telegram.png": "/img/telegram.png",
    "/img/text1.png": "/img/text1.png",
    "/img/text2.png": "/img/text2.png",
    "/img/text3.png": "/img/text3.png",
    "/img/text_bg.jpg": "/img/text_bg.jpg",
    "/img/tg.svg": "/img/tg.svg",
    "/fonts/slick.eot": "/fonts/slick.eot",
    "/fonts/slick.svg": "/fonts/slick.svg",
    "/fonts/slick.ttf": "/fonts/slick.ttf",
    "/fonts/slick.woff": "/fonts/slick.woff"
}
